nb_cli-1.6.0.dist-info/METADATA
nb_cli-1.6.0.dist-info/WHEEL
nb_cli-1.6.0.dist-info/entry_points.txt
nb_cli-1.6.0.dist-info/licenses/LICENSE
nb_cli/__init__.py
nb_cli/__main__.py
nb_cli/cli/__init__.py
nb_cli/cli/commands/__init__.py
nb_cli/cli/commands/adapter.py
nb_cli/cli/commands/cache.py
nb_cli/cli/commands/driver.py
nb_cli/cli/commands/plugin.py
nb_cli/cli/commands/project.py
nb_cli/cli/commands/self.py
nb_cli/cli/customize.py
nb_cli/cli/utils.py
nb_cli/compat.py
nb_cli/config/__init__.py
nb_cli/config/model.py
nb_cli/config/parser.py
nb_cli/consts.py
nb_cli/exceptions.py
nb_cli/extensions.py
nb_cli/handlers/__init__.py
nb_cli/handlers/adapter.py
nb_cli/handlers/data.py
nb_cli/handlers/driver.py
nb_cli/handlers/meta.py
nb_cli/handlers/pip.py
nb_cli/handlers/plugin.py
nb_cli/handlers/process.py
nb_cli/handlers/project.py
nb_cli/handlers/reloader.py
nb_cli/handlers/script.py
nb_cli/handlers/signal.py
nb_cli/handlers/store.py
nb_cli/handlers/venv.py
nb_cli/i18n.py
nb_cli/locale/zh_CN/LC_MESSAGES/nb-cli.mo
nb_cli/locale/zh_CN/LC_MESSAGES/nb-cli.po
nb_cli/log/__init__.py
nb_cli/py.typed
nb_cli/template/adapter/cookiecutter.json
nb_cli/template/adapter/{{cookiecutter.adapter_slug}}/__init__.{{cookiecutter.py}}
nb_cli/template/adapter/{{cookiecutter.adapter_slug}}/adapter.{{cookiecutter.py}}
nb_cli/template/adapter/{{cookiecutter.adapter_slug}}/bot.{{cookiecutter.py}}
nb_cli/template/adapter/{{cookiecutter.adapter_slug}}/config.{{cookiecutter.py}}
nb_cli/template/adapter/{{cookiecutter.adapter_slug}}/event.{{cookiecutter.py}}
nb_cli/template/adapter/{{cookiecutter.adapter_slug}}/message.{{cookiecutter.py}}
nb_cli/template/plugin/cookiecutter.json
nb_cli/template/plugin/hooks/post_gen_project.py
nb_cli/template/plugin/{{cookiecutter.plugin_slug}}/__init__.{{cookiecutter.py}}
nb_cli/template/plugin/{{cookiecutter.plugin_slug}}/config.{{cookiecutter.py}}
nb_cli/template/plugin/{{cookiecutter.plugin_slug}}/plugins/.gitkeep
nb_cli/template/project/bootstrap/cookiecutter.json
nb_cli/template/project/bootstrap/hooks/pre_gen_project.py
nb_cli-1.6.0.dist-info/RECORD
