Metadata-Version: 2.1
Name: nb-cli
Version: 1.6.0
Summary: CLI for nonebot2
Keywords: bot,qq,nonebot
Author-Email: yanyongyu <yyy@nonebot.dev>
License: MIT
Classifier: Development Status :: 5 - Production/Stable
Classifier: Framework :: Robot Framework
Classifier: Framework :: Robot Framework :: Library
Classifier: License :: OSI Approved :: MIT License
Classifier: Operating System :: OS Independent
Classifier: Programming Language :: Python :: 3
Project-URL: homepage, https://cli.nonebot.dev/
Project-URL: repository, https://github.com/nonebot/nb-cli
Requires-Python: <4.0,>=3.10
Requires-Dist: click~=8.1
Requires-Dist: httpx~=0.18
Requires-Dist: jinja2~=3.0
Requires-Dist: wcwidth~=0.2
Requires-Dist: tomlkit~=0.10
Requires-Dist: watchfiles~=1.0
Requires-Dist: anyio<5.0,>=3.6
Requires-Dist: cookiecutter~=2.2
Requires-Dist: virtualenv~=20.21
Requires-Dist: cashews<8.0,>=6.0
Requires-Dist: typing-extensions~=4.4
Requires-Dist: noneprompt<1.0.0,>=0.1.10
Requires-Dist: pydantic!=2.5.0,!=2.5.1,<3.0.0,>=1.10.0
Requires-Dist: nonestorage>=0.1.0
Requires-Dist: rich>=14.1.0
Requires-Dist: textual>=5.3.0
Requires-Dist: packaging>=25.0
